concoursekit/__init__.py
concoursekit-0.1.3.dist-info/LICENSE
concoursekit-0.1.3.dist-info/METADATA
concoursekit-0.1.3.dist-info/WHEEL
concoursekit-0.1.3.dist-info/entry_points.txt
concoursekit-0.1.3.dist-info/top_level.txt
concoursekit-0.1.3.dist-info/RECORD
