Metadata-Version: 2.1
Name: concoursekit
Version: 0.1.3
Summary: A Concourse CI Pipeline Generator Utility.
Home-page: https://github.com/anthonyhawkins/concourse-kit
Author: Anthony Hawkins
Author-email: ahawkins.mail@gmail.com
License: MIT
Keywords: concourse,yaml generator,pipeline manager,ci,cd
Platform: UNKNOWN
Classifier: Topic :: Software Development :: Code Generators
Classifier: License :: OSI Approved :: MIT License
Classifier: Programming Language :: Python
Classifier: Programming Language :: Python :: 3
Classifier: Programming Language :: Python :: 3 :: Only
Classifier: Programming Language :: Python :: 3.9
Requires-Python: >=3.9
License-File: LICENSE
Requires-Dist: pytoml
Requires-Dist: yamlmaker
Requires-Dist: pytest
Requires-Dist: pyyaml
